.gitignore
LICENSE.txt
README.md
TODO.md
pyproject.toml
requirements-dev.txt
requirements.txt
.github/workflows/pipy-pyblish.yaml
docs/abx17.md
docs/abxLS.md
docs/prosAudit.md
docs/sLM21.md
docs/tde17.md
examples/zr_testing.ipynb
examples/benchmark_examples/abx17.ipynb
examples/benchmark_examples/abxLS.ipynb
examples/benchmark_examples/prosAudit.ipynb
examples/benchmark_examples/sLM21.ipynb
examples/benchmark_examples/tde17.ipynb
imgs/checkpoints.png
imgs/datasets.png
imgs/samples.png
zerospeech/__init__.py
zerospeech/__main__.py
zerospeech/data_loaders.py
zerospeech/httpw.py
zerospeech/misc.py
zerospeech/networkio.py
zerospeech/out.py
zerospeech/settings.py
zerospeech/startup.py
zerospeech/benchmarks/__init__.py
zerospeech/benchmarks/_model.py
zerospeech/benchmarks/abx17.py
zerospeech/benchmarks/abxLS.py
zerospeech/benchmarks/misc.py
zerospeech/benchmarks/prosAudit.py
zerospeech/benchmarks/sLM21.py
zerospeech/benchmarks/tde17.py
zerospeech/cmd/__init__.py
zerospeech/cmd/benchmarks.py
zerospeech/cmd/checkpoints.py
zerospeech/cmd/cli_lib.py
zerospeech/cmd/datasets.py
zerospeech/cmd/generic.py
zerospeech/cmd/samples.py
zerospeech/cmd/submission.py
zerospeech/cmd/submit.py
zerospeech/cmd/user.py
zerospeech/datasets/__init__.py
zerospeech/datasets/_model.py
zerospeech/datasets/zrc_2017.py
zerospeech/datasets/zrc_2019.py
zerospeech/datasets/zrc_2021.py
zerospeech/generics/__init__.py
zerospeech/generics/checkpoints.py
zerospeech/generics/data_items.py
zerospeech/generics/named_storage.py
zerospeech/generics/repository.py
zerospeech/generics/samples.py
zerospeech/leaderboards/__init__.py
zerospeech/leaderboards/_models.py
zerospeech/leaderboards/_types.py
zerospeech/leaderboards/abx17.py
zerospeech/leaderboards/abxLS.py
zerospeech/leaderboards/prosaudit.py
zerospeech/leaderboards/sLM21.py
zerospeech/leaderboards/tde17.py
zerospeech/leaderboards/utils.py
zerospeech/leaderboards/vocolab_ext.py
zerospeech/leaderboards/exporters/__init__.py
zerospeech_benchmarks.egg-info/PKG-INFO
zerospeech_benchmarks.egg-info/SOURCES.txt
zerospeech_benchmarks.egg-info/dependency_links.txt
zerospeech_benchmarks.egg-info/entry_points.txt
zerospeech_benchmarks.egg-info/requires.txt
zerospeech_benchmarks.egg-info/top_level.txt