Metadata-Version: 2.1
Name: zerospeech-benchmarks
Version: 0.9.4
Summary: Toolset for usage of the Zero Resource Challenge Benchmarks.
Author-email: Nicolas Hamilakis <nicolas.hamilakis@ens.psl.eu>, CoML Team <dev@zerospeech.com>
License:                     GNU GENERAL PUBLIC LICENSE
Project-URL: documentation, https://zerospeech.com/toolbox/
Project-URL: homepage, https://zerospeech.com/
Project-URL: repository, https://github.com/zerospeech/benchmarks
Keywords: speech,machine-learning,challenges,research-tool,benchmark-speech,zerospeech
Classifier: Programming Language :: Python :: 3.8
Classifier: Programming Language :: Python :: 3.9
Classifier: Programming Language :: Python :: 3.10
Classifier: Programming Language :: Python :: 3.11
Classifier: Development Status :: 4 - Beta
Classifier: License :: OSI Approved :: GNU General Public License v3 or later (GPLv3+)
Classifier: Topic :: Scientific/Engineering :: Artificial Intelligence
Classifier: Intended Audience :: Science/Research
Requires-Python: >=3.8
Provides-Extra: vocolab
Provides-Extra: tts019
Provides-Extra: abx17
Provides-Extra: abxLS
Provides-Extra: tde
Provides-Extra: all
Provides-Extra: dev
License-File: LICENSE.txt
